agents/__init__.py
agents/base_agents/__init__.py
agents/base_agents/agent.py
agents/base_agents/bos_agent.py
agents/base_agents/bosii_agent.py
agents/base_agents/chicken_agent.py
agents/base_agents/cm_agent.py
agents/base_agents/lemonade_agent.py
agents/base_agents/rps_agent.py
agents/test_agents/__init__.py
agents/test_agents/chicken/__init__.py
agents/test_agents/rps/__init__.py
agt_server/__init__.py
agt_server/utils.py
agt_server/agents/__init__.py
agt_server/agents/base_agents/__init__.py
agt_server/agents/base_agents/adx_agent.py
agt_server/agents/base_agents/agent.py
agt_server/agents/base_agents/bos_agent.py
agt_server/agents/base_agents/bosii_agent.py
agt_server/agents/base_agents/chicken_agent.py
agt_server/agents/base_agents/cm_agent.py
agt_server/agents/base_agents/game_report.py
agt_server/agents/base_agents/gsvm_agent.py
agt_server/agents/base_agents/lemonade_agent.py
agt_server/agents/base_agents/lsvm_agent.py
agt_server/agents/base_agents/rps_agent.py
agt_server/agents/base_agents/sa_agent.py
agt_server/agents/test_agents/__init__.py
agt_server/agents/test_agents/adx/__init__.py
agt_server/agents/test_agents/adx/tier1/__init__.py
agt_server/agents/test_agents/adx/tier1/agent_submission.py
agt_server/agents/test_agents/adx/tier1/my_agent.py
agt_server/agents/test_agents/adx/tier2/__init__.py
agt_server/agents/test_agents/adx/tier2/agent_submission.py
agt_server/agents/test_agents/adx/tier2/my_agent.py
agt_server/agents/test_agents/adx2025/__init__.py
agt_server/agents/test_agents/adx2025/clear_logs.py
agt_server/agents/test_agents/adx2025/handin.py
agt_server/agents/test_agents/adx2025/1001/__init__.py
agt_server/agents/test_agents/adx2025/1001/agent_submission.py
agt_server/agents/test_agents/adx2025/1001/my_agent.py
agt_server/agents/test_agents/adx2025/adx_logs_2025/__init__.py
agt_server/agents/test_agents/chicken/__init__.py
agt_server/agents/test_agents/chicken/basic_agent/__init__.py
agt_server-1.10.12.dist-info/LICENSE
agt_server-1.10.12.dist-info/METADATA
agt_server-1.10.12.dist-info/WHEEL
agt_server-1.10.12.dist-info/top_level.txt
agt_server-1.10.12.dist-info/RECORD
