Metadata-Version: 2.2
Name: agt_server
Version: 1.10.12
Summary: The AGT Server is a python platform designed to run and implement game environments that autonomous agents can connect to and compete in.
Home-page: https://github.com/brown-agt/agt-server-remastered
Author: John Wu
Author-email: john_w_wu@brown.edu
Project-URL: Bug Tracker, https://github.com/brown-agt/agt-server-remastered/issues
Classifier: Programming Language :: Python :: 3
Classifier: License :: OSI Approved :: MIT License
Classifier: Operating System :: OS Independent
License-File: LICENSE
Requires-Dist: setuptools
Requires-Dist: numpy>=1.26.3
Requires-Dist: pandas
Requires-Dist: matplotlib
Requires-Dist: tqdm
Requires-Dist: pygame
Dynamic: author
Dynamic: author-email
Dynamic: classifier
Dynamic: description
Dynamic: description-content-type
Dynamic: home-page
Dynamic: project-url
Dynamic: requires-dist
Dynamic: summary
